Workbook

Sheet Обзор
A1: Навыки — прототип «Померкшая Навь»
A2: Статус | B2: [Д] черновик. Все числа — заглушки для проверки в игре. Не канон, ждёт решения директора.
A3: Откуда структура | B3: Разметка листов повторяет выгрузку PoE2DB (Активные / Поддержки / Spirit→Ауры / Meta→Божьи / Параметры). Названия, числа и механики — наши, из PoE не взято ничего.
A4: Правила | B4: docs/GDD_v1.md §4–7: камень = активный навык, метка удар/выстрел/чары, ранги D→S, поддержки в гнёзда, Ярь 100.
A5: Ранги | B5: Предложение Б (systems-wilson): гнёзд D1/C2/B2/A3/S3, +10% урона за ранг, B — Ярь −10%. Лист «Константы».
A6: Как пользоваться | B6: Синие ячейки — ввод, чёрные — формулы, зелёные — ссылки на другой лист. Меняй числа в «Параметры» и «Константы», остальное пересчитается. Жёлтые — ключевые допущения.
A7: Активных камней | B7: =COUNTA(Параметры!A2:A113)
A8: Поддержек | B8: =COUNTA(Поддержки!A2:A57)
A9: Божьих (S) | B9: =COUNTIF(Параметры!I2:I113,"S")
A10: Флаг «перегиб» | B10: =COUNTIF(Параметры!AE2:AE113,"перегиб")
A11: Флаг «слабый» | B11: =COUNTIF(Параметры!AE2:AE113,"слабый")
A13: Биом | B13: Активных / божьих / средний урон/с (без щитов и лечения)
A14: Выси (Перун, Гром) | B14: =COUNTIF(Параметры!$E$2:$E$113,"Гром")&" / "&COUNTIFS(Параметры!$E$2:$E$113,"Гром",Параметры!$I$2:$I$113,"S")&" / "&TEXT(AVERAGEIFS(Параметры!$AC$2:$AC$113,Параметры!$E$2:$E$113,"Гром",Параметры!$AC$2:$AC$113,">0"),"0")
A15: Омут (Велес, Ртуть) | B15: =COUNTIF(Параметры!$E$2:$E$113,"Ртуть")&" / "&COUNTIFS(Параметры!$E$2:$E$113,"Ртуть",Параметры!$I$2:$I$113,"S")&" / "&TEXT(AVERAGEIFS(Параметры!$AC$2:$AC$113,Параметры!$E$2:$E$113,"Ртуть",Параметры!$AC$2:$AC$113,">0"),"0")
A16: Хляби (Мокошь, Нити) | B16: =COUNTIF(Параметры!$E$2:$E$113,"Нити")&" / "&COUNTIFS(Параметры!$E$2:$E$113,"Нити",Параметры!$I$2:$I$113,"S")&" / "&TEXT(AVERAGEIFS(Параметры!$AC$2:$AC$113,Параметры!$E$2:$E$113,"Нити",Параметры!$AC$2:$AC$113,">0"),"0")
A17: Кострище (Ярило, Ярь) | B17: =COUNTIF(Параметры!$E$2:$E$113,"Ярь")&" / "&COUNTIFS(Параметры!$E$2:$E$113,"Ярь",Параметры!$I$2:$I$113,"S")&" / "&TEXT(AVERAGEIFS(Параметры!$AC$2:$AC$113,Параметры!$E$2:$E$113,"Ярь",Параметры!$AC$2:$AC$113,">0"),"0")
A18: Пекло (Чернобог, Порча) | B18: =COUNTIF(Параметры!$E$2:$E$113,"Порча")&" / "&COUNTIFS(Параметры!$E$2:$E$113,"Порча",Параметры!$I$2:$I$113,"S")&" / "&TEXT(AVERAGEIFS(Параметры!$AC$2:$AC$113,Параметры!$E$2:$E$113,"Порча",Параметры!$AC$2:$AC$113,">0"),"0")
A19: Степь (Дажьбог, Солнце) | B19: =COUNTIF(Параметры!$E$2:$E$113,"Солнце")&" / "&COUNTIFS(Параметры!$E$2:$E$113,"Солнце",Параметры!$I$2:$I$113,"S")&" / "&TEXT(AVERAGEIFS(Параметры!$AC$2:$AC$113,Параметры!$E$2:$E$113,"Солнце",Параметры!$AC$2:$AC$113,">0"),"0")
A20: Берег (Стрибог, Ветер) | B20: =COUNTIF(Параметры!$E$2:$E$113,"Ветер")&" / "&COUNTIFS(Параметры!$E$2:$E$113,"Ветер",Параметры!$I$2:$I$113,"S")&" / "&TEXT(AVERAGEIFS(Параметры!$AC$2:$AC$113,Параметры!$E$2:$E$113,"Ветер",Параметры!$AC$2:$AC$113,">0"),"0")
A21: Горнило (Сварог, Жар) | B21: =COUNTIF(Параметры!$E$2:$E$113,"Жар")&" / "&COUNTIFS(Параметры!$E$2:$E$113,"Жар",Параметры!$I$2:$I$113,"S")&" / "&TEXT(AVERAGEIFS(Параметры!$AC$2:$AC$113,Параметры!$E$2:$E$113,"Жар",Параметры!$AC$2:$AC$113,">0"),"0")
A23: Роли на биом | B23: По 2 камня на каждую из 7 ролей (Ренж-ДД, Мили-ДД, Танк, Хил, Призыв, Саппорт, Мобильность). Ранги в биоме: 6 D, 3 C, 2 B, 1 A, 2 S.
A24: Сигнатуры биомов | B24: Гром — цепь и удар в место, где враг был. Ртуть — стадо и обмен здоровья на Ярь. Нити — связь целей и деление урона. Ярь — сила при низком здоровье. Порча — «вина» и приговор. Солнце — дар по цепи союзников. Ветер — разворот снарядов и движение. Жар — турели, заготовки, зоны-правила.
A25: Открытые вопросы | B25: 1) Цвет Нитей (#D9C9A0 vs «зелень льна»). 2) Рамка иконки поддержки не утверждена артом. 3) Константы урона оружия (30/15) — допущение. 4) Ранги — ждут решения директора. 5) Пять камней и три поддержки Грома взяты из C1-Yav/*.csv без изменений.

Sheet Константы
A1: Параметр | B1: Значение | C1: Единица | D1: Источник / примечание
A2: Здоровье Отростка (базовый враг) | B2: 60 | C2: HP | D2: FNMob.h OtrostHealth [Д]
A3: Урон одного удара ближним оружием | B3: 30 | C3: урон | D3: [Д] допущение для расчёта основы «оружие ближнее»
A4: Урон одного выстрела | B4: 15 | C4: урон | D4: [Д] допущение для расчёта основы «оружие дальнее»
A5: Шкала Яри | B5: 100 | C5: Ярь | D5: GDD §4–7
A6: Ярь за убийство Отростка | B6: 20 | C6: Ярь | D6: skills_demo_v0.1
A7: Ярь за идеальный уворот (элита/босс) | B7: 25 | C7: Ярь | D7: skills_demo_v0.1 (обычный враг: 15)
A8: Регенерация Яри | B8: 1 | C8: Ярь/с | D8: skills_demo_v0.1 (3/с при 0 патронов и Ярь<20)
A9: Потолок роста урона | B9: 50 | C9: × | D9: GDD: рост урона не выше ×50
A10: Максимум More на навык | B10: 2 | C10: шт. | D10: GDD
A11: Максимальный возврат цены поддержками | B11: 0.75 | C11: доля | D11: skills_demo_v0.1
A12: Порог «перегиб» (доля эталона) | B12: 2 | C12: × | D12: [Д] флаг для балансёра
A13: Порог «слабый» (доля эталона) | B13: 0.5 | C13: × | D13: [Д] флаг для балансёра
A14: Эталон: урон на 1 Ярь | B14: =B2/B6 | C14: урон/Ярь | D14: Формула: навык за цену одного убийства (Ярь за Отростка) должен убить одного Отростка
A16: Ранги (предложение Б, systems-wilson; ждёт решения директора)
A17: Ранг | B17: Индекс | C17: Гнёзд поддержек | D17: Бонус урона (increased) | E17: Скидка Яри | F17: Источник | G17: Мир | H17: Особое
A18: D | B18: 1 | C18: 1 | D18: 0 | E18: 0 | F18: Полубог Яви | G18: Явь | H18: —
A19: C | B19: 2 | C19: 2 | D19: 0.1 | E19: 0 | F19: Полубог Яви | G19: Явь | H19: —
A20: B | B20: 3 | C20: 2 | D20: 0.2 | E20: 0.1 | F20: Полубог Нави | G20: Навь | H20: Ярь −10%
A21: A | B21: 4 | C21: 3 | D21: 0.3 | E21: 0 | F21: Полубог Нави | G21: Навь | H21: вариант формы
A22: S | B22: 5 | C22: 3 | D22: 0.4 | E22: 0 | F22: Бог Нави | G22: Навь | H22: форма + божественное свойство; слот 4

Sheet Руны
A1: Стихия | B1: Бог | C1: Биом | D1: Код | E1: Hex | F1: Цвет (для промта) | G1: Ядро (для промта) | H1: Знак по краю | I1: Знак (для промта)
A2: Гром | B2: Перун | C2: Выси | D2: 01-grom | E2: #8FA8FF | F2: lavender blue (#8FA8FF) | G2: with thin pale blue (#DDE4FF) core line | H2: зигзаг | I2: thin sharp zigzag
A3: Ртуть | B3: Велес | C3: Омут | D3: 02-rtut | E3: #B8C2C6 | F3: grey quicksilver (#B8C2C6) | G3: with thin sage green (#8FA89A) inner line | H3: капли | I3: row of small drops
A4: Нити | B4: Мокошь | C4: Хляби | D4: 03-niti | E4: #D9C9A0 | F4: unbleached linen (#D9C9A0) | H4: переплёт | I4: thin interlaced weave
A5: Ярь | B5: Ярило | C5: Кострище | D5: 04-yar | E5: #8A1020 | F5: deep crimson (#8A1020) | H5: колосья | I5: row of small wheat ears
A6: Порча | B6: Чернобог | C6: Пекло | D6: 05-porcha | E6: #2A2230 | F6: near-black violet (#2A2230) | G6: with thin murky olive (#6B6B2A) inner line | H6: пятна | I6: ring of irregular blotches
A7: Солнце | B7: Дажьбог | C7: Степь | D7: 06-solnce | E7: #FFA62B | F7: warm amber (#FFA62B) | H7: лучи | I7: ring of short sun rays
A8: Ветер | B8: Стрибог | C8: Берег | D8: 07-veter | E8: #A8D8C8 | F8: pale sea green (#A8D8C8) | H8: завиток | I8: ring of small curls
A9: Жар | B9: Сварог | C9: Горнило | D9: 08-zhar | E9: #FF6A1A | F9: forge orange (#FF6A1A) fading to dark rust (#7A2A10) | H9: зубцы-язычки | I9: ring of small flame tongues
A10: Общая | B10: — | C10: — | D10: 00-common | E10: #9A9A9A | F10: neutral stone grey (#9A9A9A) | H10: нет | I10: plain edge
A13: Глагол | B13: Узор | C13: Узор (для промта)
A14: площадь | B14: круг с точкой | C14: a circle with a dot in its center
A15: обездвиживание | B15: крест в круге | C15: a cross inside a circle
A16: цепь | B16: три точки на линии | C16: three dots on one straight line
A17: снаряд | B17: точка + черта | C17: a dot followed by a short dash
A18: дебафф | B18: перечёркнутый ромб | C18: a small diamond crossed by a slash
A19: щит | B19: полукруг-чаша | C19: a half circle open upward like a bowl, with a short vertical stroke above its center
A20: призыв | B20: фигурка-столбик | C20: a small standing post figure
A21: рывок | B21: стрела с хвостом | C21: an arrow with a feathered tail
A22: лечение | B22: росток | C22: a small sprout with two leaves
A23: аура | B23: круг из черточек | C23: a ring made of short dashes
A26: Метка | B26: Рамка | C26: Рамка (для промта)
... A30: поддержка | B30: двойное тонкое кольцо [Д] | C30: thin double ring frame
A32: Негатив-промт | B32: red-white, silver glow, neon, cyberpunk, gold, glass, text, logo, letters, cartoon, anime, 3d perspective
A33: Примечание | B33: Промт по шаблону docs/art/skills/README.md: холст 256×256, фон #1E2230, рамка по метке, узор по глаголу, знак по краю по стихии. Промты на английском — так требуют генераторы. Цвет «Нити»: взят #D9C9A0 из style_v0.1 (в art README — «зелень льна», расхождение открыто).

Sheet Активные
A1: Название | B1: Ранг | C1: Теги | D1: Биом | E1: Ярь | F1: Урон/с по откату | G1: Описание
A2: Громовой удар | B2: =INDEX(Параметры!$I$2:$I$113,MATCH($A2,Параметры!$A$2:$A$113,0)) | C2: =INDEX(Параметры!$M$2:$M$113,MATCH($A2,Параметры!$A$2:$A$113,0)) | D2: =INDEX(Параметры!$C$2:$C$113,MATCH($A2,Параметры!$A$2:$A$113,0)) | E2: =INDEX(Параметры!$AA$2:$AA$113,MATCH($A2,Параметры!$A$2:$A$113,0)) | F2: =INDEX(Параметры!$AC$2:$AC$113,MATCH($A2,Параметры!$A$2:$A$113,0)) | G2: =INDEX(Параметры!$AF$2:$AF$113,MATCH($A2,Параметры!$A$2:$A$113,0))
A3: Било | B3: =INDEX(Параметры!$I$2:$I$113,MATCH($A3,Параметры!$A$2:$A$113,0)) | C3: =INDEX(Параметры!$M$2:$M$113,MATCH($A3,Параметры!$A$2:$A$113,0)) | D3: =INDEX(Параметры!$C$2:$C$113,MATCH($A3,Параметры!$A$2:$A$113,0)) | E3: =INDEX(Параметры!$AA$2:$AA$113,MATCH($A3,Параметры!$A$2:$A$113,0)) | F3: =INDEX(Параметры!$AC$2:$AC$113,MATCH($A3,Параметры!$A$2:$A$113,0)) | G3: =INDEX(Параметры!$AF$2:$AF$113,MATCH($A3,Параметры!$A$2:$A$113,0))
A4: Цепная искра | B4: =INDEX(Параметры!$I$2:$I$113,MATCH($A4,Параметры!$A$2:$A$113,0)) | C4: =INDEX(Параметры!$M$2:$M$113,MATCH($A4,Параметры!$A$2:$A$113,0)) | D4: =INDEX(Параметры!$C$2:$C$113,MATCH($A4,Параметры!$A$2:$A$113,0)) | E4: =INDEX(Параметры!$AA$2:$AA$113,MATCH($A4,Параметры!$A$2:$A$113,0)) | F4: =INDEX(Параметры!$AC$2:$AC$113,MATCH($A4,Параметры!$A$2:$A$113,0)) | G4: =INDEX(Параметры!$AF$2:$AF$113,MATCH($A4,Параметры!$A$2:$A$113,0))
A5: Суд Перуна | B5: =INDEX(Параметры!$I$2:$I$113,MATCH($A5,Параметры!$A$2:$A$113,0)) | C5: =INDEX(Параметры!$M$2:$M$113,MATCH($A5,Параметры!$A$2:$A$113,0)) | D5: =INDEX(Параметры!$C$2:$C$113,MATCH($A5,Параметры!$A$2:$A$113,0)) | E5: =INDEX(Параметры!$AA$2:$AA$113,MATCH($A5,Параметры!$A$2:$A$113,0)) | F5: =INDEX(Параметры!$AC$2:$AC$113,MATCH($A5,Параметры!$A$2:$A$113,0)) | G5: =INDEX(Параметры!$AF$2:$AF$113,MATCH($A5,Параметры!$A$2:$A$113,0))
A6: Оберег грозы | B6: =INDEX(Параметры!$I$2:$I$113,MATCH($A6,Параметры!$A$2:$A$113,0)) | C6: =INDEX(Параметры!$M$2:$M$113,MATCH($A6,Параметры!$A$2:$A$113,0)) | D6: =INDEX(Параметры!$C$2:$C$113,MATCH($A6,Параметры!$A$2:$A$113,0)) | E6: =INDEX(Параметры!$AA$2:$AA$113,MATCH($A6,Параметры!$A$2:$A$113,0)) | F6: =INDEX(Параметры!$AC$2:$AC$113,MATCH($A6,Параметры!$A$2:$A$113,0)) | G6: =INDEX(Параметры!$AF$2:$AF$113,MATCH($A6,Параметры!$A$2:$A$113,0))
A7: Дубовая кора | B7: =INDEX(Параметры!$I$2:$I$113,MATCH($A7,Параметры!$A$2:$A$113,0)) | C7: =INDEX(Параметры!$M$2:$M$113,MATCH($A7,Параметры!$A$2:$A$113,0)) | D7: =INDEX(Параметры!$C$2:$C$113,MATCH($A7,Параметры!$A$2:$A$113,0)) | E7: =INDEX(Параметры!$AA$2:$AA$113,MATCH($A7,Параметры!$A$2:$A$113,0)) | F7: =INDEX(Параметры!$AC$2:$AC$113,MATCH($A7,Параметры!$A$2:$A$113,0)) | G7: =INDEX(Параметры!$AF$2:$AF$113,MATCH($A7,Параметры!$A$2:$A$113,0))
A8: Весть дозорного | B8: =INDEX(Параметры!$I$2:$I$113,MATCH($A8,Параметры!$A$2:$A$113,0)) | C8: =INDEX(Параметры!$M$2:$M$113,MATCH($A8,Параметры!$A$2:$A$113,0)) | D8: =INDEX(Параметры!$C$2:$C$113,MATCH($A8,Параметры!$A$2:$A$113,0)) | E8: =INDEX(Параметры!$AA$2:$AA$113,MATCH($A8,Параметры!$A$2:$A$113,0)) | F8: =INDEX(Параметры!$AC$2:$AC$113,MATCH($A8,Параметры!$A$2:$A$113,0)) | G8: =INDEX(Параметры!$AF$2:$AF$113,MATCH($A8,Параметры!$A$2:$A$113,0))
A9: Межевой дождь | B9: =INDEX(Параметры!$I$2:$I$113,MATCH($A9,Параметры!$A$2:$A$113,0)) | C9: =INDEX(Параметры!$M$2:$M$113,MATCH($A9,Параметры!$A$2:$A$113,0)) | D9: =INDEX(Параметры!$C$2:$C$113,MATCH($A9,Параметры!$A$2:$A$113,0)) | E9: =INDEX(Параметры!$AA$2:$AA$113,MATCH($A9,Параметры!$A$2:$A$113,0)) | F9: =INDEX(Параметры!$AC$2:$AC$113,MATCH($A9,Параметры!$A$2:$A$113,0)) | G9: =INDEX(Параметры!$AF$2:$AF$113,MATCH($A9,Параметры!$A$2:$A$113,0))
A10: Идол-громник | B10: =INDEX(Параметры!$I$2:$I$113,MATCH($A10,Параметры!$A$2:$A$113,0)) | C10: =INDEX(Параметры!$M$2:$M$113,MATCH($A10,Параметры!$A$2:$A$113,0)) | D10: =INDEX(Параметры!$C$2:$C$113,MATCH($A10,Параметры!$A$2:$A$113,0)) | E10: =INDEX(Параметры!$AA$2:$AA$113,MATCH($A10,Параметры!$A$2:$A$113,0)) | F10: =INDEX(Параметры!$AC$2:$AC$113,MATCH($A10,Параметры!$A$2:$A$113,0)) | G10: =INDEX(Параметры!$AF$2:$AF$113,MATCH($A10,Параметры!$A$2:$A$113,0))
A11: Громовая стрела | B11: =INDEX(Параметры!$I$2:$I$113,MATCH($A11,Параметры!$A$2:$A$113,0)) | C11: =INDEX(Параметры!$M$2:$M$113,MATCH($A11,Параметры!$A$2:$A$113,0)) | D11: =INDEX(Параметры!$C$2:$C$113,MATCH($A11,Параметры!$A$2:$A$113,0)) | E11: =INDEX(Параметры!$AA$2:$AA$113,MATCH($A11,Параметры!$A$2:$A$113,0)) | F11: =INDEX(Параметры!$AC$2:$AC$113,MATCH($A11,Параметры!$A$2:$A$113,0)) | G11: =INDEX(Параметры!$AF$2:$AF$113,MATCH($A11,Параметры!$A$2:$A$113,0))
A12: Громоотвод | B12: =INDEX(Параметры!$I$2:$I$113,MATCH($A12,Параметры!$A$2:$A$113,0)) | C12: =INDEX(Параметры!$M$2:$M$113,MATCH($A12,Параметры!$A$2:$A$113,0)) | D12: =INDEX(Параметры!$C$2:$C$113,MATCH($A12,Параметры!$A$2:$A$113,0)) | E12: =INDEX(Параметры!$AA$2:$AA$113,MATCH($A12,Параметры!$A$2:$A$113,0)) | F12: =INDEX(Параметры!$AC$2:$AC$113,MATCH($A12,Параметры!$A$2:$A$113,0)) | G12: =INDEX(Параметры!$AF$2:$AF$113,MATCH($A12,Параметры!$A$2:$A$113,0))
A13: Предгрозье | B13: =INDEX(Параметры!$I$2:$I$113,MATCH($A13,Параметры!$A$2:$A$113,0)) | C13: =INDEX(Параметры!$M$2:$M$113,MATCH($A13,Параметры!$A$2:$A$113,0)) | D13: =INDEX(Параметры!$C$2:$C$113,MATCH($A13,Параметры!$A$2:$A$113,0)) | E13: =INDEX(Параметры!$AA$2:$AA$113,MATCH($A13,Параметры!$A$2:$A$113,0)) | F13: =INDEX(Параметры!$AC$2:$AC$113,MATCH($A13,Параметры!$A$2:$A$113,0)) | G13: =INDEX(Параметры!$AF$2:$AF$113,MATCH($A13,Параметры!$A$2:$A$113,0))
... A113: Горн-скачок | B113: =INDEX(Параметры!$I$2:$I$113,MATCH($A113,Параметры!$A$2:$A$113,0)) | C113: =INDEX(Параметры!$M$2:$M$113,MATCH($A113,Параметры!$A$2:$A$113,0)) | D113: =INDEX(Параметры!$C$2:$C$113,MATCH($A113,Параметры!$A$2:$A$113,0)) | E113: =INDEX(Параметры!$AA$2:$AA$113,MATCH($A113,Параметры!$A$2:$A$113,0)) | F113: =INDEX(Параметры!$AC$2:$AC$113,MATCH($A113,Параметры!$A$2:$A$113,0)) | G113: =INDEX(Параметры!$AF$2:$AF$113,MATCH($A113,Параметры!$A$2:$A$113,0))
A115: Все значения тянутся из листа «Параметры».

Sheet Поддержки
A1: Название | B1: Тип | C1: Биом | D1: Бог | E1: Стихия | F1: Вид | G1: More (×) | H1: Мод урона | I1: Мод Яри | J1: Эффект | K1: Совместимые метки | L1: Ограничение | M1: Эфф. множитель урона | N1: Эфф. множитель на 1 Ярь | O1: Совместимых активных | P1: Знак | Q1: Описание картинки | R1: Промт иконки | S1: Статус
A2: Раскат | B2: Поддержка | C2: Выси | D2: Перун | E2: Гром | F2: механика | G2: 1 | H2: -0.5 | I2: 0 | J2: Повтор навыка через 0,6 с с уроном 50%. | K2: удар|чары | L2: — | M2: =G2*(1+H2) | N2: =IF(1+I2>0,M2/(1+I2),"за здоровье") | O2: =SUMPRODUCT(--ISNUMBER(SEARCH(Параметры!$G$2:$G$113,K2))) | P2: площадь | Q2: Двойной отзвук удара. | R2: ="Flat game UI rune icon, 256x256, centered on a dark slate (#1E2230) square tile. An outer "&INDEX(Руны!$C$27:$C$30,MATCH("поддержка",Руны!$A$27:$A$30,0))&", thick carved "&INDEX(Руны!$F$2:$F$10,MATCH(E2,Руны!$A$2:$A$10,0))&" stroke"&INDEX(Руны!$G$2:$G$10,MATCH(E2,Руны!$A$2:$A$10,0))&" and a "&INDEX(Руны!$I$2:$I$10,MATCH(E2,Руны!$A$2:$A$10,0))&" around its outside. Inside: "&INDEX(Руны!$C$14:$C$23,MATCH(P2,Руны!$A$14:$A$23,0))&". Chiseled straight line ends, flat vector, no perspective, faint outer glow." | S2: [Д] черновик
A3: Заземление | B3: Поддержка | C3: Выси | D3: Перун | E3: Гром | F3: механика | G3: 1 | H3: -0.3 | I3: 0 | J3: Каждый задетый враг возвращает 4 Ярь. | K3: удар|выстрел|чары | L3: ≤20 Ярь за применение, ≤75% цены | M3: =G3*(1+H3) | N3: =IF(1+I3>0,M3/(1+I3),"за здоровье") | O3: =SUMPRODUCT(--ISNUMBER(SEARCH(Параметры!$G$2:$G$113,K3))) | P3: обездвиживание | Q3: Шест в земле, в него стекает свет. | R3: ="Flat game UI rune icon, 256x256, centered on a dark slate (#1E2230) square tile. An outer "&INDEX(Руны!$C$27:$C$30,MATCH("поддержка",Руны!$A$27:$A$30,0))&", thick carved "&INDEX(Руны!$F$2:$F$10,MATCH(E3,Руны!$A$2:$A$10,0))&" stroke"&INDEX(Руны!$G$2:$G$10,MATCH(E3,Руны!$A$2:$A$10,0))&" and a "&INDEX(Руны!$I$2:$I$10,MATCH(E3,Руны!$A$2:$A$10,0))&" around its outside. Inside: "&INDEX(Руны!$C$14:$C$23,MATCH(P3,Руны!$A$14:$A$23,0))&". Chiseled straight line ends, flat vector, no perspective, faint outer glow." | S3: [Д] черновик
A4: Сухая гроза | B4: Поддержка | C4: Выси | D4: Перун | E4: Гром | F4: множитель | G4: 1.25 | H4: 0 | I4: 0.2 | J4: Больше урона, дороже по Яри. | K4: удар|выстрел|чары | L4: — | M4: =G4*(1+H4) | N4: =IF(1+I4>0,M4/(1+I4),"за здоровье") | O4: =SUMPRODUCT(--ISNUMBER(SEARCH(Параметры!$G$2:$G$113,K4))) | P4: площадь | Q4: Молния без капли дождя. | R4: ="Flat game UI rune icon, 256x256, centered on a dark slate (#1E2230) square tile. An outer "&INDEX(Руны!$C$27:$C$30,MATCH("поддержка",Руны!$A$27:$A$30,0))&", thick carved "&INDEX(Руны!$F$2:$F$10,MATCH(E4,Руны!$A$2:$A$10,0))&" stroke"&INDEX(Руны!$G$2:$G$10,MATCH(E4,Руны!$A$2:$A$10,0))&" and a "&INDEX(Руны!$I$2:$I$10,MATCH(E4,Руны!$A$2:$A$10,0))&" around its outside. Inside: "&INDEX(Руны!$C$14:$C$23,MATCH(P4,Руны!$A$14:$A$23,0))&". Chiseled straight line ends, flat vector, no perspective, faint outer glow." | S4: [Д] черновик
A5: Зарница | B5: Поддержка | C5: Выси | D5: Перун | E5: Гром | F5: механика | G5: 1 | H5: 0 | I5: 0.1 | J5: Перед ударом показывает метку-предупреждение; урон по месту метки +40%. | K5: чары | L5: только навыки с задержкой | M5: =G5*(1+H5) | N5: =IF(1+I5>0,M5/(1+I5),"за здоровье") | O5: =SUMPRODUCT(--ISNUMBER(SEARCH(Параметры!$G$2:$G$113,K5))) | P5: обездвиживание | Q5: Далёкая вспышка на горизонте. | R5: ="Flat game UI rune icon, 256x256, centered on a dark slate (#1E2230) square tile. An outer "&INDEX(Руны!$C$27:$C$30,MATCH("поддержка",Руны!$A$27:$A$30,0))&", thick carved "&INDEX(Руны!$F$2:$F$10,MATCH(E5,Руны!$A$2:$A$10,0))&" stroke"&INDEX(Руны!$G$2:$G$10,MATCH(E5,Руны!$A$2:$A$10,0))&" and a "&INDEX(Руны!$I$2:$I$10,MATCH(E5,Руны!$A$2:$A$10,0))&" around its outside. Inside: "&INDEX(Руны!$C$14:$C$23,MATCH(P5,Руны!$A$14:$A$23,0))&". Chiseled straight line ends, flat vector, no perspective, faint outer glow." | S5: [Д] черновик
A6: Лишний прыжок | B6: Поддержка | C6: Выси | D6: Перун | E6: Гром | F6: механика | G6: 1 | H6: -0.1 | I6: 0 | J6: +2 прыжка цепи. | K6: выстрел|чары | L6: только глагол «цепь» | M6: =G6*(1+H6) | N6: =IF(1+I6>0,M6/(1+I6),"за здоровье") | O6: =SUMPRODUCT(--ISNUMBER(SEARCH(Параметры!$G$2:$G$113,K6))) | P6: цепь | Q6: Молния прыгает ещё раз. | R6: ="Flat game UI rune icon, 256x256, centered on a dark slate (#1E2230) square tile. An outer "&INDEX(Руны!$C$27:$C$30,MATCH("поддержка",Руны!$A$27:$A$30,0))&", thick carved "&INDEX(Руны!$F$2:$F$10,MATCH(E6,Руны!$A$2:$A$10,0))&" stroke"&INDEX(Руны!$G$2:$G$10,MATCH(E6,Руны!$A$2:$A$10,0))&" and a "&INDEX(Руны!$I$2:$I$10,MATCH(E6,Руны!$A$2:$A$10,0))&" around its outside. Inside: "&INDEX(Руны!$C$14:$C$23,MATCH(P6,Руны!$A$14:$A$23,0))&". Chiseled straight line ends, flat vector, no perspective, faint outer glow." | S6: [Д] черновик
A7: Дозорный глаз | B7: Поддержка | C7: Выси | D7: Перун | E7: Гром | F7: механика | G7: 1 | H7: 0 | I7: 0 | J7: Призванный идол видит врагов за укрытием и бьёт первым. | K7: чары | L7: только призыв | M7: =G7*(1+H7) | N7: =IF(1+I7>0,M7/(1+I7),"за здоровье") | O7: =SUMPRODUCT(--ISNUMBER(SEARCH(Параметры!$G$2:$G$113,K7))) | P7: призыв | Q7: Глаз, вырезанный на столбе. | R7: ="Flat game UI rune icon, 256x256, centered on a dark slate (#1E2230) square tile. An outer "&INDEX(Руны!$C$27:$C$30,MATCH("поддержка",Руны!$A$27:$A$30,0))&", thick carved "&INDEX(Руны!$F$2:$F$10,MATCH(E7,Руны!$A$2:$A$10,0))&" stroke"&INDEX(Руны!$G$2:$G$10,MATCH(E7,Руны!$A$2:$A$10,0))&" and a "&INDEX(Руны!$I$2:$I$10,MATCH(E7,Руны!$A$2:$A$10,0))&" around its outside. Inside: "&INDEX(Руны!$C$14:$C$23,MATCH(P7,Руны!$A$14:$A$23,0))&". Chiseled straight line ends, flat vector, no perspective, faint outer glow." | S7: [Д] черновик
A8: Ртутный вес | B8: Поддержка | C8: Омут | D8: Велес | E8: Ртуть | F8: множитель | G8: 1.2 | H8: 0 | I8: 0 | J8: Снаряды тяжелее и медленнее на 20%, урон больше. | K8: выстрел|чары | L8: — | M8: =G8*(1+H8) | N8: =IF(1+I8>0,M8/(1+I8),"за здоровье") | O8: =SUMPRODUCT(--ISNUMBER(SEARCH(Параметры!$G$2:$G$113,K8))) | P8: снаряд | Q8: Капля, продавившая камень. | R8: ="Flat game UI rune icon, 256x256, centered on a dark slate (#1E2230) square tile. An outer "&INDEX(Руны!$C$27:$C$30,MATCH("поддержка",Руны!$A$27:$A$30,0))&", thick carved "&INDEX(Руны!$F$2:$F$10,MATCH(E8,Руны!$A$2:$A$10,0))&" stroke"&INDEX(Руны!$G$2:$G$10,MATCH(E8,Руны!$A$2:$A$10,0))&" and a "&INDEX(Руны!$I$2:$I$10,MATCH(E8,Руны!$A$2:$A$10,0))&" around its outside. Inside: "&INDEX(Руны!$C$14:$C$23,MATCH(P8,Руны!$A$14:$A$23,0))&". Chiseled straight line ends, flat vector, no perspective, faint outer glow." | S8: [Д] черновик
A9: Плата кровью | B9: Поддержка | C9: Омут | D9: Велес | E9: Ртуть | F9: механика | G9: 1 | H9: 0 | I9: -1 | J9: Навык стоит здоровья вместо Яри (1 Ярь = 0,5% здоровья). | K9: удар|выстрел|чары | L9: не ниже 10% здоровья | M9: =G9*(1+H9) | N9: =IF(1+I9>0,M9/(1+I9),"за здоровье") | O9: =SUMPRODUCT(--ISNUMBER(SEARCH(Параметры!$G$2:$G$113,K9))) | P9: лечение | Q9: Капля крови падает в ртуть. | R9: ="Flat game UI rune icon, 256x256, centered on a dark slate (#1E2230) square tile. An outer "&INDEX(Руны!$C$27:$C$30,MATCH("поддержка",Руны!$A$27:$A$30,0))&", thick carved "&INDEX(Руны!$F$2:$F$10,MATCH(E9,Руны!$A$2:$A$10,0))&" stroke"&INDEX(Руны!$G$2:$G$10,MATCH(E9,Руны!$A$2:$A$10,0))&" and a "&INDEX(Руны!$I$2:$I$10,MATCH(E9,Руны!$A$2:$A$10,0))&" around its outside. Inside: "&INDEX(Руны!$C$14:$C$23,MATCH(P9,Руны!$A$14:$A$23,0))&". Chiseled straight line ends, flat vector, no perspective, faint outer glow." | S9: [Д] черновик
A10: Лишний тур | B10: Поддержка | C10: Омут | D10: Велес | E10: Ртуть | F10: механика | G10: 1 | H10: -0.15 | I10: 0.15 | J10: +1 призванный зверь. | K10: чары | L10: только призыв | M10: =G10*(1+H10) | N10: =IF(1+I10>0,M10/(1+I10),"за здоровье") | O10: =SUMPRODUCT(--ISNUMBER(SEARCH(Параметры!$G$2:$G$113,K10))) | P10: призыв | Q10: Ещё одна пара рогов в стаде. | R10: ="Flat game UI rune icon, 256x256, centered on a dark slate (#1E2230) square tile. An outer "&INDEX(Руны!$C$27:$C$30,MATCH("поддержка",Руны!$A$27:$A$30,0))&", thick carved "&INDEX(Руны!$F$2:$F$10,MATCH(E10,Руны!$A$2:$A$10,0))&" stroke"&INDEX(Руны!$G$2:$G$10,MATCH(E10,Руны!$A$2:$A$10,0))&" and a "&INDEX(Руны!$I$2:$I$10,MATCH(E10,Руны!$A$2:$A$10,0))&" around its outside. Inside: "&INDEX(Руны!$C$14:$C$23,MATCH(P10,Руны!$A$14:$A$23,0))&". Chiseled straight line ends, flat vector, no perspective, faint outer glow." | S10: [Д] черновик
A11: Пастуший круг | B11: Поддержка | C11: Омут | D11: Велес | E11: Ртуть | F11: механика | G11: 1 | H11: 0 | I11: 0 | J11: Призванные держатся в 5 м от героя и прикрывают его. | K11: чары | L11: только призыв | M11: =G11*(1+H11) | N11: =IF(1+I11>0,M11/(1+I11),"за здоровье") | O11: =SUMPRODUCT(--ISNUMBER(SEARCH(Параметры!$G$2:$G$113,K11))) | P11: щит | Q11: Круг следов вокруг пастуха. | R11: ="Flat game UI rune icon, 256x256, centered on a dark slate (#1E2230) square tile. An outer "&INDEX(Руны!$C$27:$C$30,MATCH("поддержка",Руны!$A$27:$A$30,0))&", thick carved "&INDEX(Руны!$F$2:$F$10,MATCH(E11,Руны!$A$2:$A$10,0))&" stroke"&INDEX(Руны!$G$2:$G$10,MATCH(E11,Руны!$A$2:$A$10,0))&" and a "&INDEX(Руны!$I$2:$I$10,MATCH(E11,Руны!$A$2:$A$10,0))&" around its outside. Inside: "&INDEX(Руны!$C$14:$C$23,MATCH(P11,Руны!$A$14:$A$23,0))&". Chiseled straight line ends, flat vector, no perspective, faint outer glow." | S11: [Д] черновик
A12: Топь | B12: Поддержка | C12: Омут | D12: Велес | E12: Ртуть | F12: механика | G12: 1 | H12: -0.1 | I12: 0 | J12: Площадь навыка оставляет вязкую ртуть: −20% скорости на 3 с. | K12: удар|чары | L12: только глагол «площадь» | M12: =G12*(1+H12) | N12: =IF(1+I12>0,M12/(1+I12),"за здоровье") | O12: =SUMPRODUCT(--ISNUMBER(SEARCH(Параметры!$G$2:$G$113,K12))) | P12: обездвиживание | Q12: Густая ртуть на земле. | R12: ="Flat game UI rune icon, 256x256, centered on a dark slate (#1E2230) square tile. An outer "&INDEX(Руны!$C$27:$C$30,MATCH("поддержка",Руны!$A$27:$A$30,0))&", thick carved "&INDEX(Руны!$F$2:$F$10,MATCH(E12,Руны!$A$2:$A$10,0))&" stroke"&INDEX(Руны!$G$2:$G$10,MATCH(E12,Руны!$A$2:$A$10,0))&" and a "&INDEX(Руны!$I$2:$I$10,MATCH(E12,Руны!$A$2:$A$10,0))&" around its outside. Inside: "&INDEX(Руны!$C$14:$C$23,MATCH(P12,Руны!$A$14:$A$23,0))&". Chiseled straight line ends, flat vector, no perspective, faint outer glow." | S12: [Д] черновик
A13: Отдача | B13: Поддержка | C13: Омут | D13: Велес | E13: Ртуть | F13: механика | G13: 1 | H13: 0 | I13: 0 | J13: Убийство навыком возвращает 25% цены. | K13: удар|выстрел|чары | L13: ≤75% цены | M13: =G13*(1+H13) | N13: =IF(1+I13>0,M13/(1+I13),"за здоровье") | O13: =SUMPRODUCT(--ISNUMBER(SEARCH(Параметры!$G$2:$G$113,K13))) | P13: снаряд | Q13: Капля возвращается в ладонь. | R13: ="Flat game UI rune icon, 256x256, centered on a dark slate (#1E2230) square tile. An outer "&INDEX(Руны!$C$27:$C$30,MATCH("поддержка",Руны!$A$27:$A$30,0))&", thick carved "&INDEX(Руны!$F$2:$F$10,MATCH(E13,Руны!$A$2:$A$10,0))&" stroke"&INDEX(Руны!$G$2:$G$10,MATCH(E13,Руны!$A$2:$A$10,0))&" and a "&INDEX(Руны!$I$2:$I$10,MATCH(E13,Руны!$A$2:$A$10,0))&" around its outside. Inside: "&INDEX(Руны!$C$14:$C$23,MATCH(P13,Руны!$A$14:$A$23,0))&". Chiseled straight line ends, flat vector, no perspective, faint outer glow." | S13: [Д] черновик
... A57: Встряска | B57: Поддержка | C57: — | D57: — | E57: Общая | F57: механика | G57: 1 | H57: -0.1 | I57: 0 | J57: +0,3 с оглушения. | K57: удар|чары | L57: — | M57: =G57*(1+H57) | N57: =IF(1+I57>0,M57/(1+I57),"за здоровье") | O57: =SUMPRODUCT(--ISNUMBER(SEARCH(Параметры!$G$2:$G$113,K57))) | P57: обездвиживание | Q57: Трещина в щите. | R57: ="Flat game UI rune icon, 256x256, centered on a dark slate (#1E2230) square tile. An outer "&INDEX(Руны!$C$27:$C$30,MATCH("поддержка",Руны!$A$27:$A$30,0))&", thick carved "&INDEX(Руны!$F$2:$F$10,MATCH(E57,Руны!$A$2:$A$10,0))&" stroke"&INDEX(Руны!$G$2:$G$10,MATCH(E57,Руны!$A$2:$A$10,0))&" and a "&INDEX(Руны!$I$2:$I$10,MATCH(E57,Руны!$A$2:$A$10,0))&" around its outside. Inside: "&INDEX(Руны!$C$14:$C$23,MATCH(P57,Руны!$A$14:$A$23,0))&". Chiseled straight line ends, flat vector, no perspective, faint outer glow." | S57: [Д] черновик

Sheet Ауры
A1: Название | B1: Ранг | C1: Теги | D1: Биом | E1: Ярь | F1: Урон/с по откату | G1: Описание
A2: Предгрозье | B2: =INDEX(Параметры!$I$2:$I$113,MATCH($A2,Параметры!$A$2:$A$113,0)) | C2: =INDEX(Параметры!$M$2:$M$113,MATCH($A2,Параметры!$A$2:$A$113,0)) | D2: =INDEX(Параметры!$C$2:$C$113,MATCH($A2,Параметры!$A$2:$A$113,0)) | E2: =INDEX(Параметры!$AA$2:$AA$113,MATCH($A2,Параметры!$A$2:$A$113,0)) | F2: =INDEX(Параметры!$AC$2:$AC$113,MATCH($A2,Параметры!$A$2:$A$113,0)) | G2: =INDEX(Параметры!$AF$2:$AF$113,MATCH($A2,Параметры!$A$2:$A$113,0))
A3: Омутная тишь | B3: =INDEX(Параметры!$I$2:$I$113,MATCH($A3,Параметры!$A$2:$A$113,0)) | C3: =INDEX(Параметры!$M$2:$M$113,MATCH($A3,Параметры!$A$2:$A$113,0)) | D3: =INDEX(Параметры!$C$2:$C$113,MATCH($A3,Параметры!$A$2:$A$113,0)) | E3: =INDEX(Параметры!$AA$2:$AA$113,MATCH($A3,Параметры!$A$2:$A$113,0)) | F3: =INDEX(Параметры!$AC$2:$AC$113,MATCH($A3,Параметры!$A$2:$A$113,0)) | G3: =INDEX(Параметры!$AF$2:$AF$113,MATCH($A3,Параметры!$A$2:$A$113,0))
A4: Купальский круг | B4: =INDEX(Параметры!$I$2:$I$113,MATCH($A4,Параметры!$A$2:$A$113,0)) | C4: =INDEX(Параметры!$M$2:$M$113,MATCH($A4,Параметры!$A$2:$A$113,0)) | D4: =INDEX(Параметры!$C$2:$C$113,MATCH($A4,Параметры!$A$2:$A$113,0)) | E4: =INDEX(Параметры!$AA$2:$AA$113,MATCH($A4,Параметры!$A$2:$A$113,0)) | F4: =INDEX(Параметры!$AC$2:$AC$113,MATCH($A4,Параметры!$A$2:$A$113,0)) | G4: =INDEX(Параметры!$AF$2:$AF$113,MATCH($A4,Параметры!$A$2:$A$113,0))
A5: Суд над пиром | B5: =INDEX(Параметры!$I$2:$I$113,MATCH($A5,Параметры!$A$2:$A$113,0)) | C5: =INDEX(Параметры!$M$2:$M$113,MATCH($A5,Параметры!$A$2:$A$113,0)) | D5: =INDEX(Параметры!$C$2:$C$113,MATCH($A5,Параметры!$A$2:$A$113,0)) | E5: =INDEX(Параметры!$AA$2:$AA$113,MATCH($A5,Параметры!$A$2:$A$113,0)) | F5: =INDEX(Параметры!$AC$2:$AC$113,MATCH($A5,Параметры!$A$2:$A$113,0)) | G5: =INDEX(Параметры!$AF$2:$AF$113,MATCH($A5,Параметры!$A$2:$A$113,0))
A6: Полдень | B6: =INDEX(Параметры!$I$2:$I$113,MATCH($A6,Параметры!$A$2:$A$113,0)) | C6: =INDEX(Параметры!$M$2:$M$113,MATCH($A6,Параметры!$A$2:$A$113,0)) | D6: =INDEX(Параметры!$C$2:$C$113,MATCH($A6,Параметры!$A$2:$A$113,0)) | E6: =INDEX(Параметры!$AA$2:$AA$113,MATCH($A6,Параметры!$A$2:$A$113,0)) | F6: =INDEX(Параметры!$AC$2:$AC$113,MATCH($A6,Параметры!$A$2:$A$113,0)) | G6: =INDEX(Параметры!$AF$2:$AF$113,MATCH($A6,Параметры!$A$2:$A$113,0))
A7: Куда | B7: =INDEX(Параметры!$I$2:$I$113,MATCH($A7,Параметры!$A$2:$A$113,0)) | C7: =INDEX(Параметры!$M$2:$M$113,MATCH($A7,Параметры!$A$2:$A$113,0)) | D7: =INDEX(Параметры!$C$2:$C$113,MATCH($A7,Параметры!$A$2:$A$113,0)) | E7: =INDEX(Параметры!$AA$2:$AA$113,MATCH($A7,Параметры!$A$2:$A$113,0)) | F7: =INDEX(Параметры!$AC$2:$AC$113,MATCH($A7,Параметры!$A$2:$A$113,0)) | G7: =INDEX(Параметры!$AF$2:$AF$113,MATCH($A7,Параметры!$A$2:$A$113,0))
A8: Мерило | B8: =INDEX(Параметры!$I$2:$I$113,MATCH($A8,Параметры!$A$2:$A$113,0)) | C8: =INDEX(Параметры!$M$2:$M$113,MATCH($A8,Параметры!$A$2:$A$113,0)) | D8: =INDEX(Параметры!$C$2:$C$113,MATCH($A8,Параметры!$A$2:$A$113,0)) | E8: =INDEX(Параметры!$AA$2:$AA$113,MATCH($A8,Параметры!$A$2:$A$113,0)) | F8: =INDEX(Параметры!$AC$2:$AC$113,MATCH($A8,Параметры!$A$2:$A$113,0)) | G8: =INDEX(Параметры!$AF$2:$AF$113,MATCH($A8,Параметры!$A$2:$A$113,0))
A10: Аналог листа Spirit: навыки с глаголом «аура». Резерва Яри в GDD нет — аура тратит Ярь разово [Д].

Sheet Божьи
A1: Название | B1: Ранг | C1: Теги | D1: Биом | E1: Ярь | F1: Урон/с по откату | G1: Описание
A2: Суд Перуна | B2: =INDEX(Параметры!$I$2:$I$113,MATCH($A2,Параметры!$A$2:$A$113,0)) | C2: =INDEX(Параметры!$M$2:$M$113,MATCH($A2,Параметры!$A$2:$A$113,0)) | D2: =INDEX(Параметры!$C$2:$C$113,MATCH($A2,Параметры!$A$2:$A$113,0)) | E2: =INDEX(Параметры!$AA$2:$AA$113,MATCH($A2,Параметры!$A$2:$A$113,0)) | F2: =INDEX(Параметры!$AC$2:$AC$113,MATCH($A2,Параметры!$A$2:$A$113,0)) | G2: =INDEX(Параметры!$AF$2:$AF$113,MATCH($A2,Параметры!$A$2:$A$113,0))
A3: Перунов след | B3: =INDEX(Параметры!$I$2:$I$113,MATCH($A3,Параметры!$A$2:$A$113,0)) | C3: =INDEX(Параметры!$M$2:$M$113,MATCH($A3,Параметры!$A$2:$A$113,0)) | D3: =INDEX(Параметры!$C$2:$C$113,MATCH($A3,Параметры!$A$2:$A$113,0)) | E3: =INDEX(Параметры!$AA$2:$AA$113,MATCH($A3,Параметры!$A$2:$A$113,0)) | F3: =INDEX(Параметры!$AC$2:$AC$113,MATCH($A3,Параметры!$A$2:$A$113,0)) | G3: =INDEX(Параметры!$AF$2:$AF$113,MATCH($A3,Параметры!$A$2:$A$113,0))
A4: Песня пастушонка | B4: =INDEX(Параметры!$I$2:$I$113,MATCH($A4,Параметры!$A$2:$A$113,0)) | C4: =INDEX(Параметры!$M$2:$M$113,MATCH($A4,Параметры!$A$2:$A$113,0)) | D4: =INDEX(Параметры!$C$2:$C$113,MATCH($A4,Параметры!$A$2:$A$113,0)) | E4: =INDEX(Параметры!$AA$2:$AA$113,MATCH($A4,Параметры!$A$2:$A$113,0)) | F4: =INDEX(Параметры!$AC$2:$AC$113,MATCH($A4,Параметры!$A$2:$A$113,0)) | G4: =INDEX(Параметры!$AF$2:$AF$113,MATCH($A4,Параметры!$A$2:$A$113,0))
A5: Велесово стадо | B5: =INDEX(Параметры!$I$2:$I$113,MATCH($A5,Параметры!$A$2:$A$113,0)) | C5: =INDEX(Параметры!$M$2:$M$113,MATCH($A5,Параметры!$A$2:$A$113,0)) | D5: =INDEX(Параметры!$C$2:$C$113,MATCH($A5,Параметры!$A$2:$A$113,0)) | E5: =INDEX(Параметры!$AA$2:$AA$113,MATCH($A5,Параметры!$A$2:$A$113,0)) | F5: =INDEX(Параметры!$AC$2:$AC$113,MATCH($A5,Параметры!$A$2:$A$113,0)) | G5: =INDEX(Параметры!$AF$2:$AF$113,MATCH($A5,Параметры!$A$2:$A$113,0))
A6: Прядильщицы | B6: =INDEX(Параметры!$I$2:$I$113,MATCH($A6,Параметры!$A$2:$A$113,0)) | C6: =INDEX(Параметры!$M$2:$M$113,MATCH($A6,Параметры!$A$2:$A$113,0)) | D6: =INDEX(Параметры!$C$2:$C$113,MATCH($A6,Параметры!$A$2:$A$113,0)) | E6: =INDEX(Параметры!$AA$2:$AA$113,MATCH($A6,Параметры!$A$2:$A$113,0)) | F6: =INDEX(Параметры!$AC$2:$AC$113,MATCH($A6,Параметры!$A$2:$A$113,0)) | G6: =INDEX(Параметры!$AF$2:$AF$113,MATCH($A6,Параметры!$A$2:$A$113,0))
A7: Нить Мокоши | B7: =INDEX(Параметры!$I$2:$I$113,MATCH($A7,Параметры!$A$2:$A$113,0)) | C7: =INDEX(Параметры!$M$2:$M$113,MATCH($A7,Параметры!$A$2:$A$113,0)) | D7: =INDEX(Параметры!$C$2:$C$113,MATCH($A7,Параметры!$A$2:$A$113,0)) | E7: =INDEX(Параметры!$AA$2:$AA$113,MATCH($A7,Параметры!$A$2:$A$113,0)) | F7: =INDEX(Параметры!$AC$2:$AC$113,MATCH($A7,Параметры!$A$2:$A$113,0)) | G7: =INDEX(Параметры!$AF$2:$AF$113,MATCH($A7,Параметры!$A$2:$A$113,0))
A8: Дождаться | B8: =INDEX(Параметры!$I$2:$I$113,MATCH($A8,Параметры!$A$2:$A$113,0)) | C8: =INDEX(Параметры!$M$2:$M$113,MATCH($A8,Параметры!$A$2:$A$113,0)) | D8: =INDEX(Параметры!$C$2:$C$113,MATCH($A8,Параметры!$A$2:$A$113,0)) | E8: =INDEX(Параметры!$AA$2:$AA$113,MATCH($A8,Параметры!$A$2:$A$113,0)) | F8: =INDEX(Параметры!$AC$2:$AC$113,MATCH($A8,Параметры!$A$2:$A$113,0)) | G8: =INDEX(Параметры!$AF$2:$AF$113,MATCH($A8,Параметры!$A$2:$A$113,0))
A9: Ярилин разбег | B9: =INDEX(Параметры!$I$2:$I$113,MATCH($A9,Параметры!$A$2:$A$113,0)) | C9: =INDEX(Параметры!$M$2:$M$113,MATCH($A9,Параметры!$A$2:$A$113,0)) | D9: =INDEX(Параметры!$C$2:$C$113,MATCH($A9,Параметры!$A$2:$A$113,0)) | E9: =INDEX(Параметры!$AA$2:$AA$113,MATCH($A9,Параметры!$A$2:$A$113,0)) | F9: =INDEX(Параметры!$AC$2:$AC$113,MATCH($A9,Параметры!$A$2:$A$113,0)) | G9: =INDEX(Параметры!$AF$2:$AF$113,MATCH($A9,Параметры!$A$2:$A$113,0))
A10: Приговор | B10: =INDEX(Параметры!$I$2:$I$113,MATCH($A10,Параметры!$A$2:$A$113,0)) | C10: =INDEX(Параметры!$M$2:$M$113,MATCH($A10,Параметры!$A$2:$A$113,0)) | D10: =INDEX(Параметры!$C$2:$C$113,MATCH($A10,Параметры!$A$2:$A$113,0)) | E10: =INDEX(Параметры!$AA$2:$AA$113,MATCH($A10,Параметры!$A$2:$A$113,0)) | F10: =INDEX(Параметры!$AC$2:$AC$113,MATCH($A10,Параметры!$A$2:$A$113,0)) | G10: =INDEX(Параметры!$AF$2:$AF$113,MATCH($A10,Параметры!$A$2:$A$113,0))
A11: Ночь без меры | B11: =INDEX(Параметры!$I$2:$I$113,MATCH($A11,Параметры!$A$2:$A$113,0)) | C11: =INDEX(Параметры!$M$2:$M$113,MATCH($A11,Параметры!$A$2:$A$113,0)) | D11: =INDEX(Параметры!$C$2:$C$113,MATCH($A11,Параметры!$A$2:$A$113,0)) | E11: =INDEX(Параметры!$AA$2:$AA$113,MATCH($A11,Параметры!$A$2:$A$113,0)) | F11: =INDEX(Параметры!$AC$2:$AC$113,MATCH($A11,Параметры!$A$2:$A$113,0)) | G11: =INDEX(Параметры!$AF$2:$AF$113,MATCH($A11,Параметры!$A$2:$A$113,0))
A12: Незакатный взор | B12: =INDEX(Параметры!$I$2:$I$113,MATCH($A12,Параметры!$A$2:$A$113,0)) | C12: =INDEX(Параметры!$M$2:$M$113,MATCH($A12,Параметры!$A$2:$A$113,0)) | D12: =INDEX(Параметры!$C$2:$C$113,MATCH($A12,Параметры!$A$2:$A$113,0)) | E12: =INDEX(Параметры!$AA$2:$AA$113,MATCH($A12,Параметры!$A$2:$A$113,0)) | F12: =INDEX(Параметры!$AC$2:$AC$113,MATCH($A12,Параметры!$A$2:$A$113,0)) | G12: =INDEX(Параметры!$AF$2:$AF$113,MATCH($A12,Параметры!$A$2:$A$113,0))
A13: Внуки | B13: =INDEX(Параметры!$I$2:$I$113,MATCH($A13,Параметры!$A$2:$A$113,0)) | C13: =INDEX(Параметры!$M$2:$M$113,MATCH($A13,Параметры!$A$2:$A$113,0)) | D13: =INDEX(Параметры!$C$2:$C$113,MATCH($A13,Параметры!$A$2:$A$113,0)) | E13: =INDEX(Параметры!$AA$2:$AA$113,MATCH($A13,Параметры!$A$2:$A$113,0)) | F13: =INDEX(Параметры!$AC$2:$AC$113,MATCH($A13,Параметры!$A$2:$A$113,0)) | G13: =INDEX(Параметры!$AF$2:$AF$113,MATCH($A13,Параметры!$A$2:$A$113,0))
... A17: Клещи с неба | B17: =INDEX(Параметры!$I$2:$I$113,MATCH($A17,Параметры!$A$2:$A$113,0)) | C17: =INDEX(Параметры!$M$2:$M$113,MATCH($A17,Параметры!$A$2:$A$113,0)) | D17: =INDEX(Параметры!$C$2:$C$113,MATCH($A17,Параметры!$A$2:$A$113,0)) | E17: =INDEX(Параметры!$AA$2:$AA$113,MATCH($A17,Параметры!$A$2:$A$113,0)) | F17: =INDEX(Параметры!$AC$2:$AC$113,MATCH($A17,Параметры!$A$2:$A$113,0)) | G17: =INDEX(Параметры!$AF$2:$AF$113,MATCH($A17,Параметры!$A$2:$A$113,0))
A19: Аналог листа Meta: божьи камни ранга S (2 на бога), только от бога Нави; ультимейт — слот 4 в Нави.

Sheet Параметры
A1: Название | B1: Тип | C1: Биом | D1: Бог | E1: Стихия | F1: Роль | G1: Метка | H1: Глагол | I1: Ранг | J1: Мир | K1: Источник | L1: Гнёзд | M1: Теги | N1: Ярь | O1: Откат, с | P1: Урон (база) | Q1: Ударов за применение | R1: Основа урона | S1: Радиус, м | T1: Дальность, м | U1: Задержка, с | V1: Длительность, с | W1: Контроль, с | X1: Урон за применение | Y1: Бонус ранга | Z1: Урон с рангом | AA1: Ярь с рангом | AB1: Урон на 1 Ярь | AC1: Урон/с по откату | AD1: Доля эталона (по Яри) | AE1: Флаг баланса | AF1: Описание | AG1: Описание картинки | AH1: Промт иконки | AI1: Статус
A2: Громовой удар | B2: Активный | C2: Выси | D2: Перун | E2: Гром | F2: Мили-ДД | G2: удар | H2: площадь | I2: D | J2: =INDEX(Константы!$G$18:$G$22,MATCH(I2,Константы!$A$18:$A$22,0)) | K2: =INDEX(Константы!$F$18:$F$22,MATCH(I2,Константы!$A$18:$A$22,0)) | L2: =INDEX(Константы!$C$18:$C$22,MATCH(I2,Константы!$A$18:$A$22,0)) | M2: =G2&", "&H2&", "&E2&", "&F2&IF(I2="S",", Божий","") | N2: 20 | O2: 4 | P2: 1.8 | Q2: 1 | R2: оружие ближнее | S2: 4 | T2: 0 | U2: 0 | V2: 0 | W2: 0 | X2: =Q2*IF(R2="оружие ближнее",P2*Константы!$B$3,IF(R2="оружие дальнее",P2*Константы!$B$4,P2)) | Y2: =INDEX(Константы!$D$18:$D$22,MATCH(I2,Константы!$A$18:$A$22,0)) | Z2: =X2*(1+Y2) | AA2: =N2*(1-INDEX(Константы!$E$18:$E$22,MATCH(I2,Константы!$A$18:$A$22,0))) | AB2: =IF(AA2>0,Z2/AA2,0) | AC2: =IF(O2>0,Z2/O2,0) | AD2: =IF(AA2>0,AB2/Константы!$B$14,0) | AE2: =IF(Z2=0,"без урона",IF(AD2>Константы!$B$12,"перегиб",IF(AND(AA2>0,AD2<Константы!$B$13),"слабый","норма"))) | AF2: Удар оружием с разрядом: дуга 120° перед героем. | AG2: Дуга синеватых разрядов срывается с клинка, камень под ней в трещинах. | AH2: ="Flat game UI rune icon, 256x256, centered on a dark slate (#1E2230) square tile. An outer "&INDEX(Руны!$C$27:$C$30,MATCH(G2,Руны!$A$27:$A$30,0))&", thick carved "&INDEX(Руны!$F$2:$F$10,MATCH(E2,Руны!$A$2:$A$10,0))&" stroke"&INDEX(Руны!$G$2:$G$10,MATCH(E2,Руны!$A$2:$A$10,0))&" and a "&INDEX(Руны!$I$2:$I$10,MATCH(E2,Руны!$A$2:$A$10,0))&" around its outside. Inside: "&INDEX(Руны!$C$14:$C$23,MATCH(H2,Руны!$A$14:$A$23,0))&". Chiseled straight line ends, flat vector, no perspective, faint outer glow." | AI2: [Д] черновик
A3: Било | B3: Активный | C3: Выси | D3: Перун | E3: Гром | F3: Мили-ДД | G3: удар | H3: площадь | I3: B | J3: =INDEX(Константы!$G$18:$G$22,MATCH(I3,Константы!$A$18:$A$22,0)) | K3: =INDEX(Константы!$F$18:$F$22,MATCH(I3,Константы!$A$18:$A$22,0)) | L3: =INDEX(Константы!$C$18:$C$22,MATCH(I3,Константы!$A$18:$A$22,0)) | M3: =G3&", "&H3&", "&E3&", "&F3&IF(I3="S",", Божий","") | N3: 30 | O3: 9 | P3: 3 | Q3: 1 | R3: оружие ближнее | S3: 6 | T3: 0 | U3: 0.4 | V3: 0 | W3: 0.5 | X3: =Q3*IF(R3="оружие ближнее",P3*Константы!$B$3,IF(R3="оружие дальнее",P3*Константы!$B$4,P3)) | Y3: =INDEX(Константы!$D$18:$D$22,MATCH(I3,Константы!$A$18:$A$22,0)) | Z3: =X3*(1+Y3) | AA3: =N3*(1-INDEX(Константы!$E$18:$E$22,MATCH(I3,Константы!$A$18:$A$22,0))) | AB3: =IF(AA3>0,Z3/AA3,0) | AC3: =IF(O3>0,Z3/O3,0) | AD3: =IF(AA3>0,AB3/Константы!$B$14,0) | AE3: =IF(Z3=0,"без урона",IF(AD3>Константы!$B$12,"перегиб",IF(AND(AA3>0,AD3<Константы!$B$13),"слабый","норма"))) | AF3: Удар оружием в землю как в дозорное било: кольцевая волна оглушает. | AG3: Кольцо ударной волны от вбитого оружия, трещины лучами. | AH3: ="Flat game UI rune icon, 256x256, centered on a dark slate (#1E2230) square tile. An outer "&INDEX(Руны!$C$27:$C$30,MATCH(G3,Руны!$A$27:$A$30,0))&", thick carved "&INDEX(Руны!$F$2:$F$10,MATCH(E3,Руны!$A$2:$A$10,0))&" stroke"&INDEX(Руны!$G$2:$G$10,MATCH(E3,Руны!$A$2:$A$10,0))&" and a "&INDEX(Руны!$I$2:$I$10,MATCH(E3,Руны!$A$2:$A$10,0))&" around its outside. Inside: "&INDEX(Руны!$C$14:$C$23,MATCH(H3,Руны!$A$14:$A$23,0))&". Chiseled straight line ends, flat vector, no perspective, faint outer glow." | AI3: [Д] черновик
A4: Цепная искра | B4: Активный | C4: Выси | D4: Перун | E4: Гром | F4: Ренж-ДД | G4: выстрел | H4: цепь | I4: C | J4: =INDEX(Константы!$G$18:$G$22,MATCH(I4,Константы!$A$18:$A$22,0)) | K4: =INDEX(Константы!$F$18:$F$22,MATCH(I4,Константы!$A$18:$A$22,0)) | L4: =INDEX(Константы!$C$18:$C$22,MATCH(I4,Константы!$A$18:$A$22,0)) | M4: =G4&", "&H4&", "&E4&", "&F4&IF(I4="S",", Божий","") | N4: 20 | O4: 3 | P4: 1 | Q4: 1 | R4: оружие дальнее | S4: 0 | T4: 40 | U4: 0 | V4: 0 | W4: 0 | X4: =Q4*IF(R4="оружие ближнее",P4*Константы!$B$3,IF(R4="оружие дальнее",P4*Константы!$B$4,P4)) | Y4: =INDEX(Константы!$D$18:$D$22,MATCH(I4,Константы!$A$18:$A$22,0)) | Z4: =X4*(1+Y4) | AA4: =N4*(1-INDEX(Константы!$E$18:$E$22,MATCH(I4,Константы!$A$18:$A$22,0))) | AB4: =IF(AA4>0,Z4/AA4,0) | AC4: =IF(O4>0,Z4/O4,0) | AD4: =IF(AA4>0,AB4/Константы!$B$14,0) | AE4: =IF(Z4=0,"без урона",IF(AD4>Константы!$B$12,"перегиб",IF(AND(AA4>0,AD4<Константы!$B$13),"слабый","норма"))) | AF4: Выстрел искрой: 3 прыжка по соседним врагам, −25% за прыжок. | AG4: Три звена молнии между фигурами, гаснущие к концу. | AH4: ="Flat game UI rune icon, 256x256, centered on a dark slate (#1E2230) square tile. An outer "&INDEX(Руны!$C$27:$C$30,MATCH(G4,Руны!$A$27:$A$30,0))&", thick carved "&INDEX(Руны!$F$2:$F$10,MATCH(E4,Руны!$A$2:$A$10,0))&" stroke"&INDEX(Руны!$G$2:$G$10,MATCH(E4,Руны!$A$2:$A$10,0))&" and a "&INDEX(Руны!$I$2:$I$10,MATCH(E4,Руны!$A$2:$A$10,0))&" around its outside. Inside: "&INDEX(Руны!$C$14:$C$23,MATCH(H4,Руны!$A$14:$A$23,0))&". Chiseled straight line ends, flat vector, no perspective, faint outer glow." | AI4: [Д] черновик
A5: Суд Перуна | B5: Активный | C5: Выси | D5: Перун | E5: Гром | F5: Ренж-ДД | G5: чары | H5: обездвиживание | I5: S | J5: =INDEX(Константы!$G$18:$G$22,MATCH(I5,Константы!$A$18:$A$22,0)) | K5: =INDEX(Константы!$F$18:$F$22,MATCH(I5,Константы!$A$18:$A$22,0)) | L5: =INDEX(Константы!$C$18:$C$22,MATCH(I5,Константы!$A$18:$A$22,0)) | M5: =G5&", "&H5&", "&E5&", "&F5&IF(I5="S",", Божий","") | N5: 35 | O5: 25 | P5: 160 | Q5: 1 | R5: фикс | S5: 3 | T5: 30 | U5: 1 | V5: 0 | W5: 1 | X5: =Q5*IF(R5="оружие ближнее",P5*Константы!$B$3,IF(R5="оружие дальнее",P5*Константы!$B$4,P5)) | Y5: =INDEX(Константы!$D$18:$D$22,MATCH(I5,Константы!$A$18:$A$22,0)) | Z5: =X5*(1+Y5) | AA5: =N5*(1-INDEX(Константы!$E$18:$E$22,MATCH(I5,Константы!$A$18:$A$22,0))) | AB5: =IF(AA5>0,Z5/AA5,0) | AC5: =IF(O5>0,Z5/O5,0) | AD5: =IF(AA5>0,AB5/Константы!$B$14,0) | AE5: =IF(Z5=0,"без урона",IF(AD5>Константы!$B$12,"перегиб",IF(AND(AA5>0,AD5<Константы!$B$13),"слабый","норма"))) | AF5: Метит всех врагов в поле зрения; через 1 с молния бьёт туда, где они стояли в миг метки. | AG5: Столбы молний падают в светящиеся отметины, враги уже отошли от них. | AH5: ="Flat game UI rune icon, 256x256, centered on a dark slate (#1E2230) square tile. An outer "&INDEX(Руны!$C$27:$C$30,MATCH(G5,Руны!$A$27:$A$30,0))&", thick carved "&INDEX(Руны!$F$2:$F$10,MATCH(E5,Руны!$A$2:$A$10,0))&" stroke"&INDEX(Руны!$G$2:$G$10,MATCH(E5,Руны!$A$2:$A$10,0))&" and a "&INDEX(Руны!$I$2:$I$10,MATCH(E5,Руны!$A$2:$A$10,0))&" around its outside. Inside: "&INDEX(Руны!$C$14:$C$23,MATCH(H5,Руны!$A$14:$A$23,0))&". Chiseled straight line ends, flat vector, no perspective, faint outer glow." | AI5: [Д] черновик
A6: Оберег грозы | B6: Активный | C6: Выси | D6: Перун | E6: Гром | F6: Танк | G6: чары | H6: щит | I6: C | J6: =INDEX(Константы!$G$18:$G$22,MATCH(I6,Константы!$A$18:$A$22,0)) | K6: =INDEX(Константы!$F$18:$F$22,MATCH(I6,Константы!$A$18:$A$22,0)) | L6: =INDEX(Константы!$C$18:$C$22,MATCH(I6,Константы!$A$18:$A$22,0)) | M6: =G6&", "&H6&", "&E6&", "&F6&IF(I6="S",", Божий","") | N6: 35 | O6: 18 | P6: 40 | Q6: 1 | R6: фикс | S6: 4 | T6: 0 | U6: 0 | V6: 5 | W6: 0 | X6: =Q6*IF(R6="оружие ближнее",P6*Константы!$B$3,IF(R6="оружие дальнее",P6*Константы!$B$4,P6)) | Y6: =INDEX(Константы!$D$18:$D$22,MATCH(I6,Константы!$A$18:$A$22,0)) | Z6: =X6*(1+Y6) | AA6: =N6*(1-INDEX(Константы!$E$18:$E$22,MATCH(I6,Константы!$A$18:$A$22,0))) | AB6: =IF(AA6>0,Z6/AA6,0) | AC6: =IF(O6>0,Z6/O6,0) | AD6: =IF(AA6>0,AB6/Константы!$B$14,0) | AE6: =IF(Z6=0,"без урона",IF(AD6>Константы!$B$12,"перегиб",IF(AND(AA6>0,AD6<Константы!$B$13),"слабый","норма"))) | AF6: Щит в 25% здоровья на 5 с; при разрушении — разряд вокруг. | AG6: Синеватая чаша-купол над героем, по краю зигзаг. | AH6: ="Flat game UI rune icon, 256x256, centered on a dark slate (#1E2230) square tile. An outer "&INDEX(Руны!$C$27:$C$30,MATCH(G6,Руны!$A$27:$A$30,0))&", thick carved "&INDEX(Руны!$F$2:$F$10,MATCH(E6,Руны!$A$2:$A$10,0))&" stroke"&INDEX(Руны!$G$2:$G$10,MATCH(E6,Руны!$A$2:$A$10,0))&" and a "&INDEX(Руны!$I$2:$I$10,MATCH(E6,Руны!$A$2:$A$10,0))&" around its outside. Inside: "&INDEX(Руны!$C$14:$C$23,MATCH(H6,Руны!$A$14:$A$23,0))&". Chiseled straight line ends, flat vector, no perspective, faint outer glow." | AI6: [Д] черновик
A7: Дубовая кора | B7: Активный | C7: Выси | D7: Перун | E7: Гром | F7: Танк | G7: чары | H7: щит | I7: D | J7: =INDEX(Константы!$G$18:$G$22,MATCH(I7,Константы!$A$18:$A$22,0)) | K7: =INDEX(Константы!$F$18:$F$22,MATCH(I7,Константы!$A$18:$A$22,0)) | L7: =INDEX(Константы!$C$18:$C$22,MATCH(I7,Константы!$A$18:$A$22,0)) | M7: =G7&", "&H7&", "&E7&", "&F7&IF(I7="S",", Божий","") | N7: 25 | O7: 14 | P7: 0 | Q7: 1 | R7: фикс | S7: 0 | T7: 0 | U7: 0 | V7: 4 | W7: 0 | X7: =Q7*IF(R7="оружие ближнее",P7*Константы!$B$3,IF(R7="оружие дальнее",P7*Константы!$B$4,P7)) | Y7: =INDEX(Константы!$D$18:$D$22,MATCH(I7,Константы!$A$18:$A$22,0)) | Z7: =X7*(1+Y7) | AA7: =N7*(1-INDEX(Константы!$E$18:$E$22,MATCH(I7,Константы!$A$18:$A$22,0))) | AB7: =IF(AA7>0,Z7/AA7,0) | AC7: =IF(O7>0,Z7/O7,0) | AD7: =IF(AA7>0,AB7/Константы!$B$14,0) | AE7: =IF(Z7=0,"без урона",IF(AD7>Константы!$B$12,"перегиб",IF(AND(AA7>0,AD7<Константы!$B$13),"слабый","норма"))) | AF7: Кожа дубеет: −30% получаемого урона на 4 с, скорость −10%. | AG7: Фигура в трещиноватой дубовой коре, искры в трещинах. | AH7: ="Flat game UI rune icon, 256x256, centered on a dark slate (#1E2230) square tile. An outer "&INDEX(Руны!$C$27:$C$30,MATCH(G7,Руны!$A$27:$A$30,0))&", thick carved "&INDEX(Руны!$F$2:$F$10,MATCH(E7,Руны!$A$2:$A$10,0))&" stroke"&INDEX(Руны!$G$2:$G$10,MATCH(E7,Руны!$A$2:$A$10,0))&" and a "&INDEX(Руны!$I$2:$I$10,MATCH(E7,Руны!$A$2:$A$10,0))&" around its outside. Inside: "&INDEX(Руны!$C$14:$C$23,MATCH(H7,Руны!$A$14:$A$23,0))&". Chiseled straight line ends, flat vector, no perspective, faint outer glow." | AI7: [Д] черновик
A8: Весть дозорного | B8: Активный | C8: Выси | D8: Перун | E8: Гром | F8: Хил | G8: чары | H8: лечение | I8: D | J8: =INDEX(Константы!$G$18:$G$22,MATCH(I8,Константы!$A$18:$A$22,0)) | K8: =INDEX(Константы!$F$18:$F$22,MATCH(I8,Константы!$A$18:$A$22,0)) | L8: =INDEX(Константы!$C$18:$C$22,MATCH(I8,Константы!$A$18:$A$22,0)) | M8: =G8&", "&H8&", "&E8&", "&F8&IF(I8="S",", Божий","") | N8: 25 | O8: 12 | P8: 0 | Q8: 1 | R8: фикс | S8: 8 | T8: 0 | U8: 0 | V8: 0 | W8: 0 | X8: =Q8*IF(R8="оружие ближнее",P8*Константы!$B$3,IF(R8="оружие дальнее",P8*Константы!$B$4,P8)) | Y8: =INDEX(Константы!$D$18:$D$22,MATCH(I8,Константы!$A$18:$A$22,0)) | Z8: =X8*(1+Y8) | AA8: =N8*(1-INDEX(Константы!$E$18:$E$22,MATCH(I8,Константы!$A$18:$A$22,0))) | AB8: =IF(AA8>0,Z8/AA8,0) | AC8: =IF(O8>0,Z8/O8,0) | AD8: =IF(AA8>0,AB8/Константы!$B$14,0) | AE8: =IF(Z8=0,"без урона",IF(AD8>Константы!$B$12,"перегиб",IF(AND(AA8>0,AD8<Константы!$B$13),"слабый","норма"))) | AF8: Лечит героя и союзников рядом на 20% здоровья. | AG8: Вспышка дозорного огня, над ней поднимается росток света. | AH8: ="Flat game UI rune icon, 256x256, centered on a dark slate (#1E2230) square tile. An outer "&INDEX(Руны!$C$27:$C$30,MATCH(G8,Руны!$A$27:$A$30,0))&", thick carved "&INDEX(Руны!$F$2:$F$10,MATCH(E8,Руны!$A$2:$A$10,0))&" stroke"&INDEX(Руны!$G$2:$G$10,MATCH(E8,Руны!$A$2:$A$10,0))&" and a "&INDEX(Руны!$I$2:$I$10,MATCH(E8,Руны!$A$2:$A$10,0))&" around its outside. Inside: "&INDEX(Руны!$C$14:$C$23,MATCH(H8,Руны!$A$14:$A$23,0))&". Chiseled straight line ends, flat vector, no perspective, faint outer glow." | AI8: [Д] черновик
A9: Межевой дождь | B9: Активный | C9: Выси | D9: Перун | E9: Гром | F9: Хил | G9: чары | H9: лечение | I9: A | J9: =INDEX(Константы!$G$18:$G$22,MATCH(I9,Константы!$A$18:$A$22,0)) | K9: =INDEX(Константы!$F$18:$F$22,MATCH(I9,Константы!$A$18:$A$22,0)) | L9: =INDEX(Константы!$C$18:$C$22,MATCH(I9,Константы!$A$18:$A$22,0)) | M9: =G9&", "&H9&", "&E9&", "&F9&IF(I9="S",", Божий","") | N9: 35 | O9: 24 | P9: 0 | Q9: 1 | R9: фикс | S9: 6 | T9: 0 | U9: 0 | V9: 6 | W9: 0 | X9: =Q9*IF(R9="оружие ближнее",P9*Константы!$B$3,IF(R9="оружие дальнее",P9*Константы!$B$4,P9)) | Y9: =INDEX(Константы!$D$18:$D$22,MATCH(I9,Константы!$A$18:$A$22,0)) | Z9: =X9*(1+Y9) | AA9: =N9*(1-INDEX(Константы!$E$18:$E$22,MATCH(I9,Константы!$A$18:$A$22,0))) | AB9: =IF(AA9>0,Z9/AA9,0) | AC9: =IF(O9>0,Z9/O9,0) | AD9: =IF(AA9>0,AB9/Константы!$B$14,0) | AE9: =IF(Z9=0,"без урона",IF(AD9>Константы!$B$12,"перегиб",IF(AND(AA9>0,AD9<Константы!$B$13),"слабый","норма"))) | AF9: Зона дождя с межи Высей и Омута: 5% здоровья в секунду, гасит поджоги. | AG9: Косой серебристый дождь над кругом тёмной мокрой земли. | AH9: ="Flat game UI rune icon, 256x256, centered on a dark slate (#1E2230) square tile. An outer "&INDEX(Руны!$C$27:$C$30,MATCH(G9,Руны!$A$27:$A$30,0))&", thick carved "&INDEX(Руны!$F$2:$F$10,MATCH(E9,Руны!$A$2:$A$10,0))&" stroke"&INDEX(Руны!$G$2:$G$10,MATCH(E9,Руны!$A$2:$A$10,0))&" and a "&INDEX(Руны!$I$2:$I$10,MATCH(E9,Руны!$A$2:$A$10,0))&" around its outside. Inside: "&INDEX(Руны!$C$14:$C$23,MATCH(H9,Руны!$A$14:$A$23,0))&". Chiseled straight line ends, flat vector, no perspective, faint outer glow." | AI9: [Д] черновик
A10: Идол-громник | B10: Активный | C10: Выси | D10: Перун | E10: Гром | F10: Призыв | G10: чары | H10: призыв | I10: D | J10: =INDEX(Константы!$G$18:$G$22,MATCH(I10,Константы!$A$18:$A$22,0)) | K10: =INDEX(Константы!$F$18:$F$22,MATCH(I10,Константы!$A$18:$A$22,0)) | L10: =INDEX(Константы!$C$18:$C$22,MATCH(I10,Константы!$A$18:$A$22,0)) | M10: =G10&", "&H10&", "&E10&", "&F10&IF(I10="S",", Божий","") | N10: 30 | O10: 16 | P10: 12 | Q10: 10 | R10: фикс | S10: 0 | T10: 15 | U10: 0 | V10: 10 | W10: 0 | X10: =Q10*IF(R10="оружие ближнее",P10*Константы!$B$3,IF(R10="оружие дальнее",P10*Константы!$B$4,P10)) | Y10: =INDEX(Константы!$D$18:$D$22,MATCH(I10,Константы!$A$18:$A$22,0)) | Z10: =X10*(1+Y10) | AA10: =N10*(1-INDEX(Константы!$E$18:$E$22,MATCH(I10,Константы!$A$18:$A$22,0))) | AB10: =IF(AA10>0,Z10/AA10,0) | AC10: =IF(O10>0,Z10/O10,0) | AD10: =IF(AA10>0,AB10/Константы!$B$14,0) | AE10: =IF(Z10=0,"без урона",IF(AD10>Константы!$B$12,"перегиб",IF(AND(AA10>0,AD10<Константы!$B$13),"слабый","норма"))) | AF10: Резной идол на 10 с: раз в секунду бьёт молнией ближайшего врага. | AG10: Резной столб-идол с молнией в поднятой руке. | AH10: ="Flat game UI rune icon, 256x256, centered on a dark slate (#1E2230) square tile. An outer "&INDEX(Руны!$C$27:$C$30,MATCH(G10,Руны!$A$27:$A$30,0))&", thick carved "&INDEX(Руны!$F$2:$F$10,MATCH(E10,Руны!$A$2:$A$10,0))&" stroke"&INDEX(Руны!$G$2:$G$10,MATCH(E10,Руны!$A$2:$A$10,0))&" and a "&INDEX(Руны!$I$2:$I$10,MATCH(E10,Руны!$A$2:$A$10,0))&" around its outside. Inside: "&INDEX(Руны!$C$14:$C$23,MATCH(H10,Руны!$A$14:$A$23,0))&". Chiseled straight line ends, flat vector, no perspective, faint outer glow." | AI10: [Д] черновик
A11: Громовая стрела | B11: Активный | C11: Выси | D11: Перун | E11: Гром | F11: Призыв | G11: выстрел | H11: призыв | I11: C | J11: =INDEX(Константы!$G$18:$G$22,MATCH(I11,Константы!$A$18:$A$22,0)) | K11: =INDEX(Константы!$F$18:$F$22,MATCH(I11,Константы!$A$18:$A$22,0)) | L11: =INDEX(Константы!$C$18:$C$22,MATCH(I11,Константы!$A$18:$A$22,0)) | M11: =G11&", "&H11&", "&E11&", "&F11&IF(I11="S",", Божий","") | N11: 25 | O11: 14 | P11: 0.6 | Q11: 8 | R11: оружие дальнее | S11: 0 | T11: 25 | U11: 0 | V11: 8 | W11: 0 | X11: =Q11*IF(R11="оружие ближнее",P11*Константы!$B$3,IF(R11="оружие дальнее",P11*Константы!$B$4,P11)) | Y11: =INDEX(Константы!$D$18:$D$22,MATCH(I11,Константы!$A$18:$A$22,0)) | Z11: =X11*(1+Y11) | AA11: =N11*(1-INDEX(Константы!$E$18:$E$22,MATCH(I11,Константы!$A$18:$A$22,0))) | AB11: =IF(AA11>0,Z11/AA11,0) | AC11: =IF(O11>0,Z11/O11,0) | AD11: =IF(AA11>0,AB11/Константы!$B$14,0) | AE11: =IF(Z11=0,"без урона",IF(AD11>Константы!$B$12,"перегиб",IF(AND(AA11>0,AD11<Константы!$B$13),"слабый","норма"))) | AF11: Выстрел оставляет в земле громовую стрелу: 8 с стреляет искрами. | AG11: Кремнёвый наконечник торчит из земли и искрит. | AH11: ="Flat game UI rune icon, 256x256, centered on a dark slate (#1E2230) square tile. An outer "&INDEX(Руны!$C$27:$C$30,MATCH(G11,Руны!$A$27:$A$30,0))&", thick carved "&INDEX(Руны!$F$2:$F$10,MATCH(E11,Руны!$A$2:$A$10,0))&" stroke"&INDEX(Руны!$G$2:$G$10,MATCH(E11,Руны!$A$2:$A$10,0))&" and a "&INDEX(Руны!$I$2:$I$10,MATCH(E11,Руны!$A$2:$A$10,0))&" around its outside. Inside: "&INDEX(Руны!$C$14:$C$23,MATCH(H11,Руны!$A$14:$A$23,0))&". Chiseled straight line ends, flat vector, no perspective, faint outer glow." | AI11: [Д] черновик
A12: Громоотвод | B12: Активный | C12: Выси | D12: Перун | E12: Гром | F12: Саппорт | G12: чары | H12: обездвиживание | I12: D | J12: =INDEX(Константы!$G$18:$G$22,MATCH(I12,Константы!$A$18:$A$22,0)) | K12: =INDEX(Константы!$F$18:$F$22,MATCH(I12,Константы!$A$18:$A$22,0)) | L12: =INDEX(Константы!$C$18:$C$22,MATCH(I12,Константы!$A$18:$A$22,0)) | M12: =G12&", "&H12&", "&E12&", "&F12&IF(I12="S",", Божий","") | N12: 30 | O12: 10 | P12: 45 | Q12: 1 | R12: фикс | S12: 3 | T12: 8 | U12: 1.5 | V12: 0 | W12: 0.8 | X12: =Q12*IF(R12="оружие ближнее",P12*Константы!$B$3,IF(R12="оружие дальнее",P12*Константы!$B$4,P12)) | Y12: =INDEX(Константы!$D$18:$D$22,MATCH(I12,Константы!$A$18:$A$22,0)) | Z12: =X12*(1+Y12) | AA12: =N12*(1-INDEX(Константы!$E$18:$E$22,MATCH(I12,Константы!$A$18:$A$22,0))) | AB12: =IF(AA12>0,Z12/AA12,0) | AC12: =IF(O12>0,Z12/O12,0) | AD12: =IF(AA12>0,AB12/Константы!$B$14,0) | AE12: =IF(Z12=0,"без урона",IF(AD12>Константы!$B$12,"перегиб",IF(AND(AA12>0,AD12<Константы!$B$13),"слабый","норма"))) | AF12: Вбивает шест; через 1,5 с молния бьёт в точку, оглушение 0,8 с. | AG12: Железный шест, над ним тучи сходятся в воронку. | AH12: ="Flat game UI rune icon, 256x256, centered on a dark slate (#1E2230) square tile. An outer "&INDEX(Руны!$C$27:$C$30,MATCH(G12,Руны!$A$27:$A$30,0))&", thick carved "&INDEX(Руны!$F$2:$F$10,MATCH(E12,Руны!$A$2:$A$10,0))&" stroke"&INDEX(Руны!$G$2:$G$10,MATCH(E12,Руны!$A$2:$A$10,0))&" and a "&INDEX(Руны!$I$2:$I$10,MATCH(E12,Руны!$A$2:$A$10,0))&" around its outside. Inside: "&INDEX(Руны!$C$14:$C$23,MATCH(H12,Руны!$A$14:$A$23,0))&". Chiseled straight line ends, flat vector, no perspective, faint outer glow." | AI12: [Д] черновик
A13: Предгрозье | B13: Активный | C13: Выси | D13: Перун | E13: Гром | F13: Саппорт | G13: чары | H13: аура | I13: B | J13: =INDEX(Константы!$G$18:$G$22,MATCH(I13,Константы!$A$18:$A$22,0)) | K13: =INDEX(Константы!$F$18:$F$22,MATCH(I13,Константы!$A$18:$A$22,0)) | L13: =INDEX(Константы!$C$18:$C$22,MATCH(I13,Константы!$A$18:$A$22,0)) | M13: =G13&", "&H13&", "&E13&", "&F13&IF(I13="S",", Божий","") | N13: 20 | O13: 20 | P13: 0 | Q13: 1 | R13: фикс | S13: 10 | T13: 0 | U13: 0 | V13: 10 | W13: 0 | X13: =Q13*IF(R13="оружие ближнее",P13*Константы!$B$3,IF(R13="оружие дальнее",P13*Константы!$B$4,P13)) | Y13: =INDEX(Константы!$D$18:$D$22,MATCH(I13,Константы!$A$18:$A$22,0)) | Z13: =X13*(1+Y13) | AA13: =N13*(1-INDEX(Константы!$E$18:$E$22,MATCH(I13,Константы!$A$18:$A$22,0))) | AB13: =IF(AA13>0,Z13/AA13,0) | AC13: =IF(O13>0,Z13/O13,0) | AD13: =IF(AA13>0,AB13/Константы!$B$14,0) | AE13: =IF(Z13=0,"без урона",IF(AD13>Константы!$B$12,"перегиб",IF(AND(AA13>0,AD13<Константы!$B$13),"слабый","норма"))) | AF13: Аура 10 с: союзники +15% скорости атаки, враги в круге получают метку громоотвода. | AG13: Воздух дрожит кольцом, волосы героя подняты статикой. | AH13: ="Flat game UI rune icon, 256x256, centered on a dark slate (#1E2230) square tile. An outer "&INDEX(Руны!$C$27:$C$30,MATCH(G13,Руны!$A$27:$A$30,0))&", thick carved "&INDEX(Руны!$F$2:$F$10,MATCH(E13,Руны!$A$2:$A$10,0))&" stroke"&INDEX(Руны!$G$2:$G$10,MATCH(E13,Руны!$A$2:$A$10,0))&" and a "&INDEX(Руны!$I$2:$I$10,MATCH(E13,Руны!$A$2:$A$10,0))&" around its outside. Inside: "&INDEX(Руны!$C$14:$C$23,MATCH(H13,Руны!$A$14:$A$23,0))&". Chiseled straight line ends, flat vector, no perspective, faint outer glow." | AI13: [Д] черновик
... A113: Горн-скачок | B113: Активный | C113: Горнило | D113: Сварог | E113: Жар | F113: Мобильность | G113: чары | H113: рывок | I113: C | J113: =INDEX(Константы!$G$18:$G$22,MATCH(I113,Константы!$A$18:$A$22,0)) | K113: =INDEX(Константы!$F$18:$F$22,MATCH(I113,Константы!$A$18:$A$22,0)) | L113: =INDEX(Константы!$C$18:$C$22,MATCH(I113,Константы!$A$18:$A$22,0)) | M113: =G113&", "&H113&", "&E113&", "&F113&IF(I113="S",", Божий","") | N113: 25 | O113: 12 | P113: 30 | Q113: 1 | R113: фикс | S113: 3 | T113: 15 | U113: 0 | V113: 0 | W113: 0 | X113: =Q113*IF(R113="оружие ближнее",P113*Константы!$B$3,IF(R113="оружие дальнее",P113*Константы!$B$4,P113)) | Y113: =INDEX(Константы!$D$18:$D$22,MATCH(I113,Константы!$A$18:$A$22,0)) | Z113: =X113*(1+Y113) | AA113: =N113*(1-INDEX(Константы!$E$18:$E$22,MATCH(I113,Константы!$A$18:$A$22,0))) | AB113: =IF(AA113>0,Z113/AA113,0) | AC113: =IF(O113>0,Z113/O113,0) | AD113: =IF(AA113>0,AB113/Константы!$B$14,0) | AE113: =IF(Z113=0,"без урона",IF(AD113>Константы!$B$12,"перегиб",IF(AND(AA113>0,AD113<Константы!$B$13),"слабый","норма"))) | AF113: Прыжок к своей турели или заготовке; при приземлении взрыв. | AG113: Герой приземляется на наковальню, огненное кольцо. | AH113: ="Flat game UI rune icon, 256x256, centered on a dark slate (#1E2230) square tile. An outer "&INDEX(Руны!$C$27:$C$30,MATCH(G113,Руны!$A$27:$A$30,0))&", thick carved "&INDEX(Руны!$F$2:$F$10,MATCH(E113,Руны!$A$2:$A$10,0))&" stroke"&INDEX(Руны!$G$2:$G$10,MATCH(E113,Руны!$A$2:$A$10,0))&" and a "&INDEX(Руны!$I$2:$I$10,MATCH(E113,Руны!$A$2:$A$10,0))&" around its outside. Inside: "&INDEX(Руны!$C$14:$C$23,MATCH(H113,Руны!$A$14:$A$23,0))&". Chiseled straight line ends, flat vector, no perspective, faint outer glow." | AI113: [Д] черновик
